README.txt
setup.py
shipy/__init__.py
shipy/shipy.py
shipy.egg-info/PKG-INFO
shipy.egg-info/SOURCES.txt
shipy.egg-info/dependency_links.txt
shipy.egg-info/requires.txt
shipy.egg-info/top_level.txt