Metadata-Version: 1.1
Name: shipy
Version: 0.1
Summary: Multivariate Shannon Information
Home-page: https://github.com/ThePengwyn/shipy
Author: Matthew Graham
Author-email: mlwgraham1992@gmail.com
License: UNKNOWN
Download-URL: https://github.com/ThePengwyn/shipy/archive/0.01.tar.gz
Platform: UNKNOWN
Classifier: Development Status :: 3 - Alpha
Classifier: Intended Audience :: Science/Research
Classifier: License :: OSI Approved :: Apache Software License
Classifier: Programming Language :: Python :: 3
